{
	"schemaVersion": 1,
	"id": "enchantment-outline",
	"version": "${version}",
	"name": "Enchantment-Outline",
	"description": "Adds an enchantment-based item outline effect.",
	"authors": [
		"Quiet"
	],
	"contact": {
		"sources": "https://example.invalid/enchantment-outline"
	},
	"license": "CC0-1.0",
	"icon": "assets/enchantment-outline/icon.png",
	"environment": "*",
	"entrypoints": {
		"main": [
			"quiet.enchantmentoutline.EnchantmentOutline"
		],
		"client": [
			"quiet.enchantmentoutline.EnchantmentOutlineClient"
		]
	},
	"mixins": [
		{
			"config": "enchantment-outline.client.mixins.json",
			"environment": "client"
		}
	],
	"depends": {
		"fabricloader": ">=0.18.4",
		"minecraft": "~1.21.11",
		"java": ">=21",
		"fabric-api": "*"
	}
}